kupyter/__init__.py
kupyter-0.1.0.dist-info/METADATA
kupyter-0.1.0.dist-info/WHEEL
kupyter-0.1.0.dist-info/RECORD
