Metadata-Version: 2.3
Name: kupyter
Version: 0.1.0
Summary: Add a short description here
Author-email: fecet <xiezej@gmail.com>
Requires-Python: >=3.10
